matchain/__init__.py
matchain/__main__.py
matchain/api.py
matchain/base.py
matchain/blocking.py
matchain/chain.py
matchain/config.py
matchain/evaluate.py
matchain/graph.py
matchain/mtoken.py
matchain/predict.py
matchain/prepare.py
matchain/preprocess.py
matchain/similarity.py
matchain/util.py
matchain/word2vec.py
matchain/alg/__init__.py
matchain/alg/autocal/__init__.py
matchain/alg/autocal/autocal.py
matchain/res/__init__.py
matchain/res/logging_info.yaml
matchain/res/mccommands_sdt_shg.yaml
matchain/res/mcdatasets_sdt_shg.yaml
matchain-0.1.2.dist-info/LICENSE.txt
matchain-0.1.2.dist-info/METADATA
matchain-0.1.2.dist-info/WHEEL
matchain-0.1.2.dist-info/top_level.txt
matchain-0.1.2.dist-info/RECORD
