Metadata-Version: 2.1
Name: matchain
Version: 0.1.2
Summary: Record linkage - simple, flexible, efficient.
Author: Andreas Eibeck
License: BSD-3-Clause
Project-URL: repository, https://github.com/ae3000/matchain
Keywords: record linkage,instance matching
Classifier: License :: OSI Approved :: BSD License
Classifier: Programming Language :: Python :: 3.8
Classifier: Programming Language :: Python :: 3.9
Classifier: Programming Language :: Python :: 3.10
Classifier: Programming Language :: Python :: 3.11
Requires-Python: >=3.8.16
License-File: LICENSE.txt
Requires-Dist: networkx >=2.8.8
Requires-Dist: tqdm >=4.49.0
Requires-Dist: numpy >=1.22.4
Requires-Dist: pandas >=1.5.3
Requires-Dist: scikit-learn >=1.1.2
Requires-Dist: scipy >=1.7.1
Requires-Dist: gensim >=4.2.0
Requires-Dist: thefuzz >=0.19.0
Requires-Dist: levenshtein >=0.22.0
Requires-Dist: sentence-transformers >=2.2.2
Requires-Dist: nmslib >=2.1.1
Requires-Dist: sparse-dot-topn >=0.3.4
Requires-Dist: faiss-cpu >=1.7.4
